csv_splitter/__init__.py
csv_splitter/splitter.py
webengage_csv_split-0.1.0.dist-info/METADATA
webengage_csv_split-0.1.0.dist-info/WHEEL
webengage_csv_split-0.1.0.dist-info/entry_points.txt
webengage_csv_split-0.1.0.dist-info/top_level.txt
webengage_csv_split-0.1.0.dist-info/RECORD
