Metadata-Version: 2.1
Name: webengage-csv-split
Version: 0.1.0
Summary: Webengage internal tool to split CSV files having huge data into multiple parts
Home-page: https://www.webengage.com/
Author: Nipun Patel
Author-email: nipunp27@gmail.com
License: MIT
Classifier: Programming Language :: Python :: 3
Classifier: License :: OSI Approved :: MIT License
Classifier: Operating System :: OS Independent
Requires-Python: >=3.6
Requires-Dist: pandas
